MANIFEST.in
README
git_backup.py
requirements.txt
setup.py
git_backup.egg-info/PKG-INFO
git_backup.egg-info/SOURCES.txt
git_backup.egg-info/dependency_links.txt
git_backup.egg-info/entry_points.txt
git_backup.egg-info/requires.txt
git_backup.egg-info/top_level.txt