Metadata-Version: 1.1
Name: git-backup
Version: 0.1
Summary: Script for backing up GitHub repositories
Home-page: https://github.com/KonishchevDmitry/git-backup
Author: Dmitry Konishchev
Author-email: konishchev@gmail.com
License: GPL3
Platform: linux
Platform: osx
Classifier: Development Status :: 4 - Beta
Classifier: Environment :: Console
Classifier: Intended Audience :: Developers
Classifier: Intended Audience :: System Administrators
Classifier: License :: OSI Approved :: GNU General Public License v3 or later (GPLv3+)
Classifier: Natural Language :: English
Classifier: Operating System :: MacOS
Classifier: Operating System :: POSIX :: Linux
Classifier: Programming Language :: Python :: 2
Classifier: Programming Language :: Python :: 3
Classifier: Topic :: Software Development :: Version Control
Classifier: Topic :: System :: Archiving :: Backup
Classifier: Topic :: System :: Archiving :: Mirroring
Classifier: Topic :: Utilities
